denoiseg/__init__.py
denoiseg/version.py
denoiseg/_test/__init__.py
denoiseg/_test/test_denoiseg_data_preprocessing.py
denoiseg/internals/DenoiSeg_DataWrapper.py
denoiseg/internals/__init__.py
denoiseg/internals/losses.py
denoiseg/models/__init__.py
denoiseg/models/denoiseg_config.py
denoiseg/models/denoiseg_standard.py
denoiseg/utils/__init__.py
denoiseg/utils/compute_precision_threshold.py
denoiseg/utils/denoiseg_data_preprocessing.py
denoiseg/utils/misc_utils.py
denoiseg/utils/seg_utils.py
denoiseg-0.3.1.dist-info/LICENSE.txt
denoiseg-0.3.1.dist-info/METADATA
denoiseg-0.3.1.dist-info/WHEEL
denoiseg-0.3.1.dist-info/top_level.txt
denoiseg-0.3.1.dist-info/RECORD
